skifts/__init__.py
skifts/_array2d.py
skifts/_fts.py
skifts-0.1.0.dist-info/LICENSE
skifts-0.1.0.dist-info/METADATA
skifts-0.1.0.dist-info/WHEEL
skifts-0.1.0.dist-info/top_level.txt
skifts-0.1.0.dist-info/RECORD
