Metadata-Version: 2.1
Name: skifts
Version: 0.1.0
Summary: Search for the most relevant documents containing words from a query
Home-page: https://github.com/rtmigo/skifts_py#readme
Author: Artёm IG
Author-email: ortemeo@gmail.com
License: MIT
Keywords: information-retrieval,text-mining,numpy,tf-idf,cosine-similarity
Platform: UNKNOWN
Classifier: Development Status :: 3 - Alpha
Classifier: License :: OSI Approved :: MIT License
Classifier: Programming Language :: Python :: 3.6
Classifier: Programming Language :: Python :: 3.7
Classifier: Programming Language :: Python :: 3.8
Classifier: Programming Language :: Python :: 3.9
Classifier: Programming Language :: Python :: 3.10
Requires-Python: >=3.6
License-File: LICENSE
Requires-Dist: scikit-learn
